app/__init__.py
app/gui.py
app/main.py
clipboard_files-1.0.19.dist-info/METADATA
clipboard_files-1.0.19.dist-info/WHEEL
clipboard_files-1.0.19.dist-info/entry_points.txt
clipboard_files-1.0.19.dist-info/top_level.txt
clipboard_files-1.0.19.dist-info/RECORD
