Metadata-Version: 2.1
Name: clipboard-files
Version: 1.0.19
Summary: A script for copying file contents to the clipboard. cf is the command
Home-page: UNKNOWN
Author: Nadav Goldstein
License: UNKNOWN
Platform: UNKNOWN
Requires-Dist: pyperclip
